delftdashboard/__init__.py
delftdashboard/app.py
delftdashboard/delftdashboard_gui.py
delftdashboard/config/Combinear.qss
delftdashboard/config/delftdashboard.ini
delftdashboard/config/colormaps/earth.txt
delftdashboard/config/images/DelftDashBoard.jpg
delftdashboard/config/images/deltares_icon.png
delftdashboard/layers/__init__.py
delftdashboard/layers/layers.py
delftdashboard/layers/config/layers.yml
delftdashboard/menu/__init__.py
delftdashboard/menu/coordinate_system.py
delftdashboard/menu/file.py
delftdashboard/menu/help.py
delftdashboard/menu/model.py
delftdashboard/menu/toolbox.py
delftdashboard/menu/topography.py
delftdashboard/menu/view.py
delftdashboard/misc/__init__.py
delftdashboard/misc/xml2yml.py
delftdashboard/misc/cyclone_track_selector/cyclone_track_selector.py
delftdashboard/misc/cyclone_track_selector/cyclone_track_selector.yml
delftdashboard/misc/select_utm_zone/__init__.py
delftdashboard/misc/select_utm_zone/callbacks.py
delftdashboard/misc/select_utm_zone/utm_zone.yml
delftdashboard/models/__init__.py
delftdashboard/models/hurrywave/__init__.py
delftdashboard/models/hurrywave/boundary_conditions.py
delftdashboard/models/hurrywave/domain.py
delftdashboard/models/hurrywave/hurrywave.py
delftdashboard/models/hurrywave/meteo.py
delftdashboard/models/hurrywave/numerics.py
delftdashboard/models/hurrywave/observation_points_regular.py
delftdashboard/models/hurrywave/observation_points_spectra.py
delftdashboard/models/hurrywave/output.py
delftdashboard/models/hurrywave/physics_constants.py
delftdashboard/models/hurrywave/physics_meteo.py
delftdashboard/models/hurrywave/physics_roughness.py
delftdashboard/models/hurrywave/structures.py
delftdashboard/models/hurrywave/timeframe.py
delftdashboard/models/hurrywave/config/boundary_conditions.yml
delftdashboard/models/hurrywave/config/domain.yml
delftdashboard/models/hurrywave/config/hurrywave.yml
delftdashboard/models/hurrywave/config/meteo.yml
delftdashboard/models/hurrywave/config/numerics.yml
delftdashboard-0.3.1.dist-info/LICENSE
delftdashboard-0.3.1.dist-info/METADATA
delftdashboard-0.3.1.dist-info/WHEEL
delftdashboard-0.3.1.dist-info/top_level.txt
delftdashboard-0.3.1.dist-info/RECORD
